pyspark_testing/__init__.py
pyspark_testing/testing/__init__.py
pyspark_testing/testing/dataframe.py
tests/__init__.py
tests/test_dataframe.py
pyspark_testing-0.0.5.dist-info/LICENSE
pyspark_testing-0.0.5.dist-info/METADATA
pyspark_testing-0.0.5.dist-info/WHEEL
pyspark_testing-0.0.5.dist-info/top_level.txt
pyspark_testing-0.0.5.dist-info/RECORD
